MANIFEST.in
README.md
setup.cfg
setup.py
install/__init__.py
install/createKernel.py
install/generate.py
install/pixiedustapp.py
install/templates/LICENSE.tpl
install/templates/MANIFEST.intpl
install/templates/header.tpl
install/templates/readme.mdtpl
install/templates/setup.cfgtpl
install/templates/setup.pytpl
install/templates/chart/__init__.pytpl
install/templates/chart/rendererBaseDisplay.pytpl
install/templates/chart/rendererDisplay.pytpl
install/templates/display/__init__.pytpl
install/templates/display/display.pytpl
install/templates/display/helloWorld.htmltpl
pixiedust/__init__.py
pixiedust/proxyShell.py
pixiedust.egg-info/PKG-INFO
pixiedust.egg-info/SOURCES.txt
pixiedust.egg-info/dependency_links.txt
pixiedust.egg-info/entry_points.txt
pixiedust.egg-info/not-zip-safe
pixiedust.egg-info/requires.txt
pixiedust.egg-info/top_level.txt
pixiedust/apps/__init__.py
pixiedust/apps/cfBrowser.py
pixiedust/apps/cloudantBrowser.py
pixiedust/apps/connectionWidget.py
pixiedust/apps/mapboxBase.py
pixiedust/apps/mongoBrowser.py
pixiedust/apps/debugger/__init__.py
pixiedust/apps/debugger/pixieDebugger.py
pixiedust/apps/debugger/templates/mainScreen.html
pixiedust/apps/debugger/templates/toolbar.html
pixiedust/apps/gateway/__init__.py
pixiedust/apps/gateway/publish.py
pixiedust/apps/gateway/share.py
pixiedust/apps/gateway/templates/mainOptions.html
pixiedust/apps/gateway/templates/publishBasicOptions.html
pixiedust/apps/gateway/templates/publishImportOptions.html
pixiedust/apps/gateway/templates/publishKernelSpecOptions.html
pixiedust/apps/gateway/templates/publishSecurityOptions.html
pixiedust/apps/gateway/templates/shareBasicOptions.html
pixiedust/apps/gateway/templates/sharePermissionsOptions.html
pixiedust/apps/gateway/templates/shareRefreshOptions.html
pixiedust/apps/messageHub/__init__.py
pixiedust/apps/messageHub/messageHubApp.py
pixiedust/apps/template/__init__.py
pixiedust/apps/template/tabbed.py
pixiedust/apps/watsonML/__init__.py
pixiedust/apps/watsonML/watsonMLApp.py
pixiedust/display/__init__.py
pixiedust/display/display.py
pixiedust/display/streamingDisplay.py
pixiedust/display/app/__init__.py
pixiedust/display/app/pixieapp.py
pixiedust/display/chart/__init__.py
