Metadata-Version: 1.0
Name: pixiedust
Version: 1.1.17
Summary: Productivity library for Jupyter Notebook
Home-page: https://github.com/pixiedust/pixiedust
Author: David Taieb
Author-email: david_taieb@us.ibm.com
License: Apache 2.0
Platform: UNKNOWN
